aoe_opening_data/__init__.py
aoe_opening_data/aoe_replay_stats.py
aoe_opening_data/create_statistics.py
aoe_opening_data/grab_replays_for_player.py
aoe_opening_data/parse_replays_and_store_in_db.py
aoe_opening_data/send_data_to_server.py
aoe_opening_data/aoe2techtree/data/data.json
aoe_opening_data/aoe2techtree/data/locales/en/strings.json
aoe_opening_data-1.0.13.dist-info/LICENSE
aoe_opening_data-1.0.13.dist-info/METADATA
aoe_opening_data-1.0.13.dist-info/WHEEL
aoe_opening_data-1.0.13.dist-info/top_level.txt
aoe_opening_data-1.0.13.dist-info/RECORD
