Metadata-Version: 2.1
Name: aoe-opening-data
Version: 1.0.13
Summary: Extract opening information for AoE2:DE replays
Home-page: https://github.com/dj0wns/AoE_Rec_Opening_Analysis
Author: dj0wns
Author-email: derekjones@asu.edu
License: MIT
Classifier: License :: OSI Approved :: MIT License
Classifier: Operating System :: OS Independent
Classifier: Programming Language :: Python :: 3
License-File: LICENSE
Requires-Dist: construct (==2.8.16)
Requires-Dist: mgz (>=1.7.5)
Requires-Dist: python-dotenv (==0.20.0)
Requires-Dist: requests (==2.27.1)
